[{"codigo":3058,"descripcion":"CIUDAD AUTONOMA BUENOS AIRES - CIUDAD AUTONOMA BUENOS AIRES"},{"codigo":3,"descripcion":"12 DE AGOSTO - BUENOS AIRES"},{"codigo":4,"descripcion":"12 DE OCTUBRE - BUENOS AIRES"},{"codigo":5,"descripcion":"16 DE JULIO - BUENOS AIRES"},{"codigo":6,"descripcion":"17 DE AGOSTO - BUENOS AIRES"},{"codigo":11,"descripcion":"20 DE JUNIO - BUENOS AIRES"},{"codigo":16,"descripcion":"25 DE MAYO - BUENOS AIRES"},{"codigo":24,"descripcion":"30 DE AGOSTO - BUENOS AIRES"},{"codigo":29,"descripcion":"9 DE ABRIL - BUENOS AIRES"},{"codigo":30,"descripcion":"9 DE JULIO - BUENOS AIRES"},{"codigo":32,"descripcion":"ABASTO - BUENOS AIRES"},{"codigo":33,"descripcion":"ABBOTT - BUENOS AIRES"},{"codigo":36,"descripcion":"ABEL - BUENOS AIRES"},{"codigo":68,"descripcion":"ACAMBUCO - BUENOS AIRES"},{"codigo":71,"descripcion":"ACASSUSO - BUENOS AIRES"},{"codigo":74,"descripcion":"ACEILAN - BUENOS AIRES"},{"codigo":77,"descripcion":"ACEVEDO - BUENOS AIRES"},{"codigo":85,"descripcion":"ACHUPALLAS - BUENOS AIRES"},{"codigo":95,"descripcion":"ADELA - BUENOS AIRES"},{"codigo":98,"descripcion":"ADELA SAENZ - BUENOS AIRES"},{"codigo":99,"descripcion":"ADOLFO ALSINA - BUENOS AIRES"},{"codigo":101,"descripcion":"ADOLFO GONZALES CHAVES - BUENOS AIRES"},{"codigo":108,"descripcion":"AEROPUERTO EZEIZA - BUENOS AIRES"},{"codigo":112,"descripcion":"AGOTE - BUENOS AIRES"},{"codigo":207,"descripcion":"AGUAS CORRIENTES - BUENOS AIRES"},{"codigo":214,"descripcion":"AGUAS VERDES - BUENOS AIRES"},{"codigo":221,"descripcion":"AGUIRREZABALA - BUENOS AIRES"},{"codigo":223,"descripcion":"AGUSTIN MOSCONI - BUENOS AIRES"},{"codigo":225,"descripcion":"AGUSTINA - BUENOS AIRES"},{"codigo":235,"descripcion":"ALAGON - BUENOS AIRES"}]